nbcommon/__init__.py
nbcommon/aiorequests.py
nbcommon/geo.py
nbcommon/model.py
nbcommon/osrmapi.py
nbcommon/statsd.py
nbcommon/test_geo.py
nbcommon/test_model.py
nbcommon/test_osrmapi.py
nbcommon/test_util.py
nbcommon/util.py
nbcommon-0.1.57.dist-info/LICENSE
nbcommon-0.1.57.dist-info/METADATA
nbcommon-0.1.57.dist-info/WHEEL
nbcommon-0.1.57.dist-info/top_level.txt
nbcommon-0.1.57.dist-info/RECORD
