Metadata-Version: 2.1
Name: nbcommon
Version: 0.1.57
Summary: nbcommon pkgs
Home-page: UNKNOWN
Author: chang@nextbillion.ai
Author-email: chang@nextbillion.ai
License: UNKNOWN
Platform: UNKNOWN
Classifier: Programming Language :: Python :: 3
Classifier: License :: OSI Approved :: MIT License
Classifier: Operating System :: OS Independent
Requires-Python: >=3.6
Requires-Dist: PyYAML (>=5.1.2)
Requires-Dist: pydantic (>=1.5)
Requires-Dist: aiohttp (>=3.6.2)
Requires-Dist: osrmfb (>=0.1.0)
Requires-Dist: prometheus-client (>=0.7.1)
